setup.py
udbq.py
udbq.egg-info/PKG-INFO
udbq.egg-info/SOURCES.txt
udbq.egg-info/dependency_links.txt
udbq.egg-info/top_level.txt