Metadata-Version: 2.1
Name: udbq
Version: 0.0.0
Summary: Minimalist Python database query builder / anti-ORM.
Home-page: https://github.com/pfalcon/udbq
Author: Paul Sokolovsky
Author-email: pfalcon@users.sourceforge.net
License: MIT
